gptlabelwrapper/__init__.py
gptlabelwrapper/_nbdev.py
gptlabelwrapper/core.py
label_wrapper/__init__.py
label_wrapper/_nbdev.py
label_wrapper/core.py
gptlabelwrapper-0.0.2.dist-info/LICENSE
gptlabelwrapper-0.0.2.dist-info/METADATA
gptlabelwrapper-0.0.2.dist-info/WHEEL
gptlabelwrapper-0.0.2.dist-info/entry_points.txt
gptlabelwrapper-0.0.2.dist-info/top_level.txt
gptlabelwrapper-0.0.2.dist-info/RECORD
