Metadata-Version: 2.1
Name: gptlabelwrapper
Version: 0.0.2
Summary: build prompts for gpt
Home-page: https://github.com/fun-with-prompts/gptlabelwrapper/tree/master/
Author: gpt_prompts
Author-email: openaipromptzoo@gmail.com
License: Apache Software License 2.0
Keywords: gpt,prompts wrapper
Platform: UNKNOWN
Classifier: Development Status :: 2 - Pre-Alpha
Classifier: Intended Audience :: Developers
Classifier: License :: OSI Approved :: Apache Software License
Classifier: Natural Language :: English
Classifier: Programming Language :: Python :: 3.6
Classifier: Programming Language :: Python :: 3.7
Classifier: Programming Language :: Python :: 3.8
Requires-Python: >=3.6
Requires-Dist: openai
Requires-Dist: pandas
Requires-Dist: numpy
